ravityemaillib/__init__.py
ravityemaillib/emaillib.py
ravityemaillib-0.1.1.3.dist-info/METADATA
ravityemaillib-0.1.1.3.dist-info/WHEEL
ravityemaillib-0.1.1.3.dist-info/top_level.txt
ravityemaillib-0.1.1.3.dist-info/RECORD
