Metadata-Version: 2.1
Name: ravityemaillib
Version: 0.1.1.3
Summary: Ravity Custom Libraries
Home-page: UNKNOWN
Author: Me
License: MIT
Platform: UNKNOWN
